Metadata-Version: 1.0
Name: tarun-probdist
Version: 0.0.1
Summary: Gaussian distributions
Home-page: UNKNOWN
Author: Tharun Saranga
Author-email: tarun.saranga116@gmail.com
License: UNKNOWN
Platform: UNKNOWN
